obwikilink/__init__.py
obwikilink/core.py
obwikilink-1.0.2.dist-info/METADATA
obwikilink-1.0.2.dist-info/WHEEL
obwikilink-1.0.2.dist-info/top_level.txt
obwikilink-1.0.2.dist-info/RECORD
