Metadata-Version: 2.4
Name: obwikilink
Version: 1.0.2
Summary: Add your description here
Requires-Python: >=3.10
Requires-Dist: pytest>=8.4.1
Requires-Dist: toml>=0.10.2
